va_am/__init__.py
va_am/__main__.py
va_am/va_am.py
va_am/utils/AutoEncoders.py
va_am/utils/__init__.py
va_am/utils/functions.py
va_am-1.0.1.dist-info/licenses/LICENCE
va_am-1.0.1.dist-info/METADATA
va_am-1.0.1.dist-info/WHEEL
va_am-1.0.1.dist-info/entry_points.txt
va_am-1.0.1.dist-info/top_level.txt
va_am-1.0.1.dist-info/RECORD
