Metadata-Version: 2.4
Name: va_am
Version: 1.0.1
Summary: VA-AM method implementation
Author-email: cosminmarina <cosmin.marina@uah.es>
Project-URL: Homepage, https://github.com/cosminmarina/va-am
Project-URL: Documentation, https://va-am.readthedocs.io/
Classifier: License :: OSI Approved :: GNU General Public License v3 (GPLv3)
Classifier: Programming Language :: Python
Classifier: Programming Language :: Python :: 3
Requires-Python: >=3.7
License-File: LICENCE
Requires-Dist: requests
Requires-Dist: sympy
Requires-Dist: keras
Requires-Dist: tensorflow
Requires-Dist: xarray
Requires-Dist: netcdf4
Requires-Dist: matplotlib
Requires-Dist: pandas
Requires-Dist: numpy
Dynamic: license-file
